{
  "id": "a0W2x000004zkdsEAA",
  "slug": "a0w2x000004zkdseaa",
  "title": "令和4年度 訪日外国人旅行者受入環境整備緊急対策事業費補助金 宿泊施設インバウンド対応支援事業(バリアフリー分野)",
  "overview": "バリアフリー",
  "detail": "<p><strong style=\"color: rgb(0, 111, 173);\">■目的・概要</strong></p><p><span style=\"color: rgb(62, 62, 60);\">訪日外国人旅行者４，０００万人、６，０００万人の実現に向けて、訪日外国人旅行者が安心して快適に滞在できる環境を整備するため、宿泊施設におけるインバウンド対応及びバリアフリー化を実施する事業（以下「宿泊施設インバウンド対応支援事業」という。）に対して、民間団体等（以下「補助対象事業者」という。）が、その費用負担を軽減するため当該経費の一部を助成する事業（以下「補助事業」という。）等に要する経費を補助することにより、訪日外国人旅行者の受入環境整備を行うための緊急対策を促進することを目的とする。</span></p><p><br></p><p><strong style=\"color: rgb(0, 111, 173);\">■根拠法令</strong></p><p><span style=\"color: rgb(62, 62, 60); font-size: 10pt;\">訪日外国人旅行者受入環境整備緊急対策事業費補助金交付要綱</span></p><p><br></p><p><strong style=\"color: rgb(0, 111, 173);\">■応募資格</strong></p><p>宿泊事業者</p><p><br></p><p><strong style=\"color: rgb(0, 111, 173);\">■問合せ先</strong></p><p>株式会社ＪＴＢ　霞が関事業部</p><p>宿泊施設インバウンド対応支援事業事務局</p><p>住所：〒100-6051</p><p>東京都千代田区霞が関3-2-5　霞が関ビル23階</p><p>電話：03-6737-9262</p><p><br></p><p>受付時間：10：00～12：00,13:00～17：00（土曜日、日曜日、祝日を除く）</p><p>※お問い合わせの受付は、公募が開始されてからとなります。</p>",
  "region": "national",
  "prefectures": [],
  "industries": [
    "宿泊業",
    "飲食サービス業"
  ],
  "targetNumberOfEmployees": "従業員数の制約なし",
  "employeeMin": null,
  "employeeMax": null,
  "purposes": [
    "設備投資",
    "デジタル化"
  ],
  "usePurpose": "設備整備・IT導入をしたい",
  "status": "closed",
  "workflow": "令和4年度 訪日外国人旅行者受入環境整備緊急対策事業費補助金",
  "subsidizedRate": "1/2",
  "upperLimit": "5,000,000円",
  "lowerLimit": null,
  "startDate": "2022-06-30",
  "endDate": "2022-10-12",
  "source": "jgrants",
  "referenceUrl": "https://www.jgrants-portal.go.jp/subsidy/a0W2x000004zkdsEAA",
  "updatedAt": "2026-04-19T18:29:14.920Z"
}