{
  "id": "a0W2x000003R8BOEA0",
  "slug": "a0w2x000003r8boea0",
  "title": "令和3年度_低炭素型ディーゼルトラック普及加速化事業",
  "overview": "",
  "detail": "<p><span style=\"color: rgb(62, 62, 60); font-size: 10.5pt;\">　一般財団法人環境優良車普及機構（以下「機構」という。）では、環境省から二酸化炭素排出抑制対策事業費等補助金（低炭素型ディーゼルトラック普及加速化事業）の交付決定を受け、機構が管理・運用する補助金を活用して、トラック輸送における二酸化炭素の排出削減を図り、もって地球環境保全に資することを目的として、低炭素型ディーゼルトラックを導入する事業者に対して補助金を交付する事業を実施することとしています。</span></p><p><span style=\"color: rgb(62, 62, 60); font-size: 10.5pt;\">　本補助金の概要、対象事業、応募方法及びその他の留意事項は、</span><a href=\"http://levo.or.jp/fukyu/hojokin/r3/pdf/15kouboyouryou.pdf\" target=\"_blank\">公募要領</a>に記載するとおりですので、応募される方は、公募要領を熟読のうえ、二酸化炭素排出抑制対策事業費等補助金（低炭素型ディーゼルトラック普及加速化事業）<a href=\"http://levo.or.jp/fukyu/hojokin/r3/pdf/16koufukitei.pdf\" target=\"_blank\">交付規程</a>（令和 3 年5月　日環執行3-003号）に従って手続きを行っていただくようお願いいたします。</p><p><br></p><p><b style=\"color: rgb(0, 111, 173); font-size: 10.5pt;\">■目的と性格</b></p><p><span style=\"color: rgb(62, 62, 60); font-size: 10.5pt;\">・この補助金は、中小トラック事業者が低炭素型ディーゼルトラックを導入する事業を支援することにより、トラック輸送においてエコドライブを含む燃費改善のための取組を継続的に実施・改善する体制を構築することで二酸化炭素排出削減を図り、もって地球環境保全に資することを目的としています。</span></p><p><span style=\"color: rgb(62, 62, 60); font-size: 10.5pt;\"> </span></p><p><span style=\"color: rgb(62, 62, 60); font-size: 10.5pt;\">・事業の実施によるエネルギー起源二酸化炭素の排出量が確実に削減されることが重要です。このため、事業完了後は事業報告書（燃費改善効果及び二酸化炭素削減効果の実績把握）の提出をしていただくことになります。また適正な財産管理、補助事業である旨の表示(車両へのステッカーの貼付)などが必要です。</span></p><p><span style=\"color: rgb(62, 62, 60); font-size: 10.5pt;\"> </span></p><p><span style=\"color: rgb(62, 62, 60); font-size: 10.5pt;\">・これらの義務が十分果たされないときは、機構より改善のための指導を行うとともに、事態の重大なものについては交付決定を解除することもあります。また、新たな申請を受理しない場合もあります。</span></p><p><span style=\"color: rgb(62, 62, 60); font-size: 10.5pt;\"> </span></p><p><b style=\"color: rgb(0, 111, 173); font-size: 10.5pt;\">■応募資格</b></p><p><span style=\"color: rgb(62, 62, 60); font-size: 10.5pt;\">　低炭素型ディーゼルトラックの補助金を受けることができるのは、以下①又は②のいずれかに該当する者が補助対象事業者になります。</span></p><p><span style=\"color: rgb(62, 62, 60); font-size: 10.5pt;\"> </span></p><p><span style=\"color: rgb(62, 62, 60); font-size: 10.5pt;\">　① 以下のア～ウに該当する者であって、中小企業基本法（昭和３８年法律第１５４号）第２条第１項第１号に掲げる中小企業者(資本金３億円以下又は従業員数３００人以下)であること</span></p><p class=\"ql-indent-1\"><span style=\"color: rgb(62, 62, 60); font-size: 10.5pt;\">ア　一般貨物自動車運送事業者</span></p><p class=\"ql-indent-1\"><span style=\"color: rgb(62, 62, 60); font-size: 10.5pt;\">イ　特定貨物自動車運送事業者</span></p><p class=\"ql-indent-1\"><span style=\"color: rgb(62, 62, 60); font-size: 10.5pt;\">ウ　第二種貨物利用運送事業者</span></p><p><span style=\"color: rgb(62, 62, 60); font-size: 10.5pt;\"> </span></p><p><span style=\"color: rgb(62, 62, 60); font-size: 10.5pt;\">　② 上記①に貸渡す自動車リース事業者</span></p><p><span style=\"color: rgb(62, 62, 60); font-size: 10.5pt;\"> </span></p><p><b style=\"color: rgb(0, 111, 173); font-size: 10.5pt;\">■補助対象・補助額</b></p><p><span style=\"color: rgb(51, 51, 51); font-size: 10.5pt;\">　令和３年４月１日～令和４年１月３１日までに新車新規登録し、平成27年度重量車燃費基準を大型車は＋5％以上、中型車及び小型車は＋10％以上達成した車両。具体的な対象車両区分と対象排出ガス規制識別記号、および補助額は下表のとおりです。</span></p><p><span style=\"font-family: sans-serif;\"><img src=\"https://jgrants-portal.file.force.com/servlet/rtaImage?eid=a0W2x000003R8BO&amp;feoid=00N2x000008J0KS&amp;refid=0EM2x000000fiN4\" alt=\"排ガス識別記号と補助額_R3.jpg\"></img></span></p><p class=\"ql-indent-1\"><span style=\"background-color: white; color: rgb(51, 51, 51); font-size: 10.5pt;\">※廃車の要件等については、</span><a href=\"http://www.levo.or.jp/fukyu/hojokin/r3/pdf2/shinsakijun.pdf\" target=\"_blank\" style=\"background-color: white; color: rgb(247, 3, 3); font-size: 10.5pt;\">審査基準</a><span style=\"background-color: white; color: rgb(51, 51, 51); font-size: 10.5pt;\">をご参照ください。</span></p><p><br></p><p><b style=\"background-color: white; color: rgb(0, 111, 173); font-size: 10.5pt;\">■申請台数</b></p><p><span style=\"background-color: white; color: rgb(62, 62, 60); font-size: 10.5pt;\">　1事業者あたり2台　※提出書類は1台につき一式必要となります。</span></p><p><br></p><p><b style=\"background-color: white; color: rgb(0, 111, 173); font-size: 10.5pt;\">■予算総額</b></p><p><span style=\"background-color: white; color: rgb(62, 62, 60); font-size: 10.5pt;\">　28億円</span></p><p><br></p><p><b style=\"color: rgb(0, 111, 173); font-size: 10.5pt;\">■参照URL</b></p><p><span style=\"color: rgb(62, 62, 60); font-size: 10.5pt;\">　</span><a href=\"http://levo.or.jp/fukyu/hojokin/r3_index.html\" target=\"_blank\" style=\"color: rgb(62, 62, 60); font-size: 12px; font-family: sans-serif;\">http://www.levo.or.jp/fukyu/hojokin/r3_index.html</a></p><p><br></p><p><b style=\"color: rgb(0, 111, 173); font-family: Tahoma, sans-serif; font-size: 10.5pt;\">﻿</b><b style=\"color: rgb(0, 111, 173); font-size: 10.5pt;\">■備考</b></p><p><span style=\"color: black; font-size: 10.5pt;\">　ｊＧｒａｎｔｓからの申請が使用できるのは、補助対象事業者様です。代理人による申請はできません。</span></p><p><br></p><p><b style=\"color: rgb(0, 111, 173); font-size: 10.5pt;\">■問合せ先</b></p><p><span style=\"color: rgb(51, 51, 51); font-size: 10.5pt;\">　一般財団法人環境優良車普及機構</span></p><p><span style=\"color: rgb(51, 51, 51); font-size: 10.5pt;\">　「低炭素型ディーゼル車普及事業」執行グループ</span></p><p><span style=\"color: rgb(51, 51, 51); font-size: 10.5pt;\">　・電　話 ：　０３－５３４１－４５７７</span></p><p><span style=\"color: rgb(51, 51, 51); font-size: 10.5pt;\">　・ＦＡＸ ：　０３－５３４１－４５７８</span></p><p><span style=\"color: rgb(51, 51, 51); font-size: 10.5pt;\">　・Ｅ-mail：　</span><a href=\"mailto:hojokin@levo.or.jp\" target=\"_blank\" style=\"color: rgb(101, 126, 41); font-size: 12px; background-color: white; font-family: sans-serif;\">hojokin@levo.or.jp</a></p>",
  "region": "national",
  "prefectures": [],
  "industries": [
    "運輸業",
    "郵便業",
    "金融業",
    "保険業"
  ],
  "targetNumberOfEmployees": "従業員数の制約なし",
  "employeeMin": null,
  "employeeMax": null,
  "purposes": [
    "設備投資",
    "創業",
    "省エネ"
  ],
  "usePurpose": "エコ・SDGs活動支援がほしい",
  "status": "closed",
  "workflow": "二酸化炭素排出抑制対策事業費等補助金",
  "subsidizedRate": "公募要領を参照",
  "upperLimit": "750,000円",
  "lowerLimit": null,
  "startDate": "2021-05-28",
  "endDate": "2022-01-31",
  "source": "jgrants",
  "referenceUrl": "https://www.jgrants-portal.go.jp/subsidy/a0W2x000003R8BOEA0",
  "updatedAt": "2026-04-19T18:29:14.338Z"
}