{
  "id": "a0W2x000003QX7EEAW",
  "slug": "a0w2x000003qx7eeaw",
  "title": "【東京都】燃料電池バスの導入促進事業",
  "overview": "",
  "detail": "<p><b style=\"color: rgb(0, 111, 173);\">■目的・概要（サマリ）:</b></p><p>水素エネルギーが活用された水素社会の早期実現に向けて、燃料電池バスの普及促進を図るため燃料電池バスの購入費の一部を助成します。</p><p><br></p><p><b style=\"color: rgb(0, 111, 173);\">■目的・概要:</b></p><p>燃料電池バスの導入促進事業は、公益財団法人東京都環境公社が、旅客自動車運送事業者等が燃料電池バスを導入するに当たり、その経費の一部を助成することにより、水素エネルギーが活用された水素社会の早期実現に向けて事業用の燃料電池バスの普及を促進することを目的に実施するものです。</p><p><br></p><p><b style=\"color: rgb(0, 111, 173);\">■問い合わせ先:</b></p><p>公益財団法人東京都環境公社</p><p>東京都地球温暖化防止活動推進センター（略称：クール・ネット東京）</p><p>都市エネ促進チーム　電話：03-5990-5159（午前９時から午後５時まで）</p><p><br></p><p><b style=\"color: rgb(0, 111, 173);\">■参照URL:</b></p><p>事業の概要はこちら</p><p><a href=\"https://www.tokyo-co2down.jp/company/subsidy/fc-bus/index.html\" target=\"_blank\">https://www.tokyo-co2down.jp/company/subsidy/fc-bus/index.html</a></p><p>詳細はホームページに掲載している手引きをご覧ください</p>",
  "region": "tokyo",
  "prefectures": [
    "東京都"
  ],
  "industries": [
    "サービス業（他に分類されないもの）",
    "運輸業",
    "郵便業"
  ],
  "employeeMin": null,
  "employeeMax": null,
  "purposes": [
    "設備投資",
    "省エネ",
    "デジタル化"
  ],
  "status": "closed",
  "workflow": "燃料電池バスの導入促進事業",
  "subsidizedRate": "交付要綱参照",
  "upperLimit": "50,000,000円",
  "lowerLimit": null,
  "startDate": "2021-09-27",
  "endDate": "2022-03-31",
  "source": "jgrants",
  "referenceUrl": "https://www.jgrants-portal.go.jp/subsidy/a0W2x000003QX7EEAW",
  "updatedAt": "2026-04-19T18:29:13.485Z"
}