{
  "id": "a0W2x000005j4lPEAQ",
  "slug": "a0w2x000005j4lpeaq",
  "title": "感染症対策サポート助成事業（消耗品購入コース）",
  "overview": "感染症対策に係る消耗品購入経費の一部を支援します！",
  "detail": "<p><strong style=\"color: rgb(0, 111, 173);\">■目的・概要</strong></p><p><strong>（１）コロナ対策リーダー、認証店枠</strong></p><p>東京都による研修を修了したコロナ対策リーダーを配置している店舗もしくは感染防止徹底点検済証の交付を受けている店舗において事業者が取り組む新型コロナウイルス感染防止対策に係る消耗品の購入費用を助成することで、経済活動との両立を図りながら、感染症対策の取組をさらに推進することを目的としています。</p><p><strong>（２）一般枠</strong></p><p>新型コロナウイルス感染症対策に係る消耗品を、都内中小企業者等が購入する場合に助成することで、都内中小企業者等による経済活動の推進に寄与することを目的としています。</p><p><br></p><p><strong style=\"color: rgb(0, 111, 173);\">■助成対象者</strong></p><p><strong style=\"color: rgb(0, 0, 0);\">（１）コロナ対策リーダー、認証店枠</strong></p><p>コロナ対策リーダーを配置している都内店舗又は感染防止徹底点検済証の交付を受けている店舗を運営する都内中小企業者（会社及び個人事業者）、一般財団法人、一般社団法人、特定非営利活動法人（NPO法人）</p><p>※飲食店の営業許可証を有する店舗であること</p><p><strong>（２）一般枠</strong></p><p>都内中小企業者（会社及び個人事業者）、一般財団法人、一般社団法人、特定非営利活動法人（NPO法人）、中小企業団体等</p><p><br></p><p>※医療法人、社会福祉法人、学校法人、商工会、商工会連合会、商工会議所、公益財団法人、公益社団法人、商店街振興組合、宗教法人は対象外です。</p><p><br></p><p><strong style=\"color: rgb(0, 111, 173);\">■助成率</strong></p><p><strong style=\"color: rgb(0, 0, 0);\">（１）コロナ対策リーダー、認証店枠</strong></p><p>助成対象と認められる経費の５分の４以内（千円未満は切り捨て）</p><p><strong>（２）一般枠</strong></p><p>助成対象と認められる経費の３分の２以内（千円未満は切り捨て）</p><p><br></p><p><strong style=\"color: rgb(0, 111, 173);\">■助成対象経費</strong></p><p>感染予防対策に係る消耗品購入経費の一部</p><p><br></p><p><strong style=\"color: rgb(0, 111, 173);\">■助成限度額</strong></p><p><strong style=\"color: rgb(0, 0, 0);\">（１）コロナ対策リーダー、認証店枠</strong></p><p>１店舗あたり１０万円（都内のコロナ対策リーダー配置店舗または認証店に限ります）</p><p><strong>（２）一般枠</strong></p><p>１事業所あたり１０万円（都内事業所に限ります）</p><p><br></p><p><strong style=\"color: rgb(0, 111, 173);\">■助成対象期間</strong></p><p>令和４年１月１日（土）～令和５年５月７日（日）</p><p>この期間内に購入、納品、支払までを完了する必要があります。</p><p><br></p><p><strong style=\"color: rgb(0, 111, 173);\">■問合せ先</strong></p><p>公益財団法人東京都中小企業振興公社</p><p>感染症対策サポート助成事業事務局</p><p>電話番号：０３－４３３５－７９９０</p><p><br></p><p><strong style=\"color: rgb(0, 111, 173);\">■参照URL</strong></p><p><a href=\"https://www.tokyo-kosha.or.jp/support/josei/jigyo/final/kansentaisaku.html\" target=\"_blank\" style=\"color: rgb(17, 85, 204); font-family: Arial, Helvetica, sans-serif; font-size: small; background-color: rgb(255, 255, 255);\">https://www.tokyo-kosha.or.jp/support/josei/jigyo/final/kansentaisaku.html</a></p><p><br></p><p><strong style=\"color: rgb(0, 111, 173);\">■備考</strong></p><p>・助成金にはルールがあります。申請に先立ち、かならず上記WEBページに掲載されている「募集要項」をお読みいただきますようお願いいたします。</p><p>・「コロナ対策リーダー、認証店枠」は、申請店舗が異なれば、１事業者当たり複数回の申請をすることは可能ですが、同一店舗への助成は１回限りとなります（コロナ対策リーダーが変更となっても再度の助成はできません）。</p><p>・「一般枠」は、１事業者１採択となりますので、複数の事業所を申請したい場合はまとめて申請してください。</p>",
  "region": "tokyo",
  "prefectures": [
    "東京都"
  ],
  "industries": [
    "漁業",
    "建設業",
    "製造業",
    "電気・ガス・熱供給・水道業",
    "情報通信業",
    "複合サービス事業",
    "サービス業（他に分類されないもの）",
    "分類不能の産業",
    "農業",
    "林業",
    "鉱業",
    "採石業",
    "砂利採取業",
    "運輸業",
    "郵便業",
    "卸売業",
    "小売業",
    "金融業",
    "保険業",
    "不動産業",
    "物品賃貸業",
    "学術研究",
    "専門・技術サービス業",
    "宿泊業",
    "飲食サービス業",
    "生活関連サービス業",
    "娯楽業",
    "教育",
    "学習支援業",
    "医療",
    "福祉"
  ],
  "employeeMin": null,
  "employeeMax": 300,
  "purposes": [
    "設備投資"
  ],
  "status": "closed",
  "workflow": "感染症対策サポート助成事業",
  "subsidizedRate": "５分の４または３分の２",
  "upperLimit": "100,000円",
  "lowerLimit": null,
  "startDate": "2022-01-21",
  "endDate": "2023-05-07",
  "source": "jgrants",
  "referenceUrl": "https://www.jgrants-portal.go.jp/subsidy/a0W2x000005j4lPEAQ",
  "updatedAt": "2026-04-19T18:29:15.442Z"
}