{
  "id": "a0WJ200000CDYC2MAP",
  "slug": "a0wj200000cdyc2map",
  "title": "中小企業等収益力向上（賃上げ環境整備）事業費補助金",
  "overview": "収益力の向上を目指す新たな取組を支援します！",
  "detail": "<p><strong style=\"color: rgb(0, 111, 173);\">■目的・概要</strong></p><p>中小企業者等の収益力向上と持続的発展を図り、賃上げの継続と成長を促進するため、経営環境の変化に対応し、</p><p>独自の技術やサービス展開を目指す取組を行う中小企業者等に対し、予算の範囲内において、補助金を交付します。</p><p><br></p><p><strong style=\"color: rgb(0, 111, 173);\">■問合せ先</strong></p><p>中小企業等収益力向上（賃上げ環境整備）事業費補助金事務局</p><p>TEL：0570-056106</p><p>Mail：jimukyoku@shuekiryoku-chinage.jp</p><p><br></p><p><strong style=\"color: rgb(0, 111, 173);\">■参照URL</strong></p><p><a href=\"https://www.ric-shizuoka.or.jp/keiei/shuekiryoku-chinage.html\" target=\"_blank\">https://www.ric-shizuoka.or.jp/keiei/shuekiryoku-chinage.html</a></p>",
  "region": "prefecture",
  "prefectures": [
    "静岡県"
  ],
  "industries": [
    "漁業",
    "建設業",
    "製造業",
    "電気・ガス・熱供給・水道業",
    "情報通信業",
    "複合サービス事業",
    "サービス業（他に分類されないもの）",
    "分類不能の産業",
    "農業",
    "林業",
    "鉱業",
    "採石業",
    "砂利採取業",
    "運輸業",
    "郵便業",
    "卸売業",
    "小売業",
    "金融業",
    "保険業",
    "不動産業",
    "物品賃貸業",
    "学術研究",
    "専門・技術サービス業",
    "宿泊業",
    "飲食サービス業",
    "生活関連サービス業",
    "娯楽業",
    "教育",
    "学習支援業",
    "医療",
    "福祉"
  ],
  "employeeMin": null,
  "employeeMax": 900,
  "purposes": [
    "設備投資",
    "人材育成",
    "販路拡大",
    "研究開発",
    "デジタル化"
  ],
  "status": "open",
  "workflow": "中小企業等収益力向上（賃上げ環境整備）事業費補助金",
  "subsidizedRate": "1/2～２/3以内　※補助額や補助率は、枠や賃金引上げ要件の有無によって異なります。",
  "upperLimit": "10,000,000円",
  "lowerLimit": null,
  "startDate": "2026-04-01",
  "endDate": "2026-05-15",
  "source": "jgrants",
  "referenceUrl": "https://www.jgrants-portal.go.jp/subsidy/a0WJ200000CDYC2MAP",
  "updatedAt": "2026-04-19T18:29:28.563Z"
}