{
  "id": "a0WJ200000CDN2pMAH",
  "slug": "a0wj200000cdn2pmah",
  "title": "小規模事業者持続化補助金＜創業型＞ 第１回受付締切",
  "overview": "小規模事業者持続化補助金＜創業型＞ 第１回受付締切",
  "detail": "<p style=\"text-align: center;\"><strong>---------------------------------------------------------------------------------------</strong></p><p style=\"text-align: center;\"><strong style=\"color: rgb(255, 0, 0); font-size: 14px;\">【申請方法について】</strong></p><p style=\"text-align: center;\"><strong>申請方法につきましては、下記リンクをクリックしご確認ください。</strong></p><p style=\"text-align: center;\"><a href=\"https://r6.jizokukahojokin.info/sogyo/doc/r6_jtebiki_sogyo1.pdf\" target=\"_blank\" style=\"font-size: 20px;\"><strong>Ｊグランツ申請入力手引き</strong></a></p><p style=\"text-align: center;\"><strong>下部にある参照リンクも必ずご確認ください。</strong></p><p style=\"text-align: center;\"><strong>---------------------------------------------------------------------------------------</strong></p><p><strong style=\"font-size: 16px; color: rgb(0, 111, 173);\">【電子申請システム「jGrants」の利用環境】</strong></p><p><span style=\"color: rgb(0, 0, 0); font-size: 16px;\">jGrantsの動作環境は以下のとおりです。下記のブラウザの最新バージョンをご利用ください。</span></p><p><span style=\"color: rgb(0, 0, 0); font-size: 16px;\">● Windows　：Google Chrome, Microsoft Edge</span></p><p><span style=\"font-size: 16px; color: rgb(0, 0, 0);\">● macOS　　：Google Chrome, Safari</span></p><p><span style=\"font-size: 16px; color: rgb(0, 0, 0);\">● iOS　　　　：Safari</span></p><p><span style=\"font-size: 16px; color: rgb(0, 0, 0);\">● Android　　：Google Chrome</span></p><p><span style=\"color: rgb(0, 0, 0); font-size: 16px;\">※上記以外のブラウザは、申請上のエラー等が生じますので利用しないでください。</span></p><p><span style=\"font-size: 16px; color: rgb(0, 0, 0);\">※Microsoft Edge の「Internet Explorer モード」は申請上のエラー等が生じますので</span></p><p><span style=\"font-size: 16px; color: rgb(0, 0, 0);\">　利用しないでください。</span></p><p><br></p><p><span style=\"color: rgb(0, 0, 0); font-size: 16px;\">※添付書類については、pdf 、zip 、png 、bmp 、jpg 、jpeg 、gif 、heic 、doc 、</span></p><p><span style=\"color: rgb(0, 0, 0); font-size: 16px;\">　docx 、xls 、xlsx で作成してください。</span></p><p><br></p><p><br></p><p><strong style=\"font-size: 16px; color: rgb(0, 111, 173);\">■目的・概要</strong></p><p><span style=\"color: rgb(0, 0, 0); font-size: 16px;\">創業後３年以内の事業者を重点的に支援するため、産業競争力強化法に基づく</span></p><p><span style=\"color: rgb(0, 0, 0); font-size: 16px;\">「認定市区町村」または「認定市区町村」と連携した「認定連携創業支援等事業者」が</span></p><p><span style=\"color: rgb(0, 0, 0); font-size: 16px;\">実施した「特定創業支援等事業」による支援を受けた事業者が、今後複数年にわたり</span></p><p><span style=\"color: rgb(0, 0, 0); font-size: 16px;\">相次いで直面する制度変更等に対応するために取り組む販路開拓等の取組の経費の一部を</span></p><p><span style=\"color: rgb(0, 0, 0); font-size: 16px;\">補助することにより、地域の雇用や産業を支える小規模事業者等の生産性向上と</span></p><p><span style=\"color: rgb(0, 0, 0); font-size: 16px;\">持続的発展を図ることを目的とします。</span></p><p><span style=\"color: rgb(0, 0, 0); font-size: 16px;\">本補助金事業は、自ら策定した持続的な経営に向けた経営計画に基づく、</span></p><p><span style=\"color: rgb(0, 0, 0); font-size: 16px;\">販路開拓等の取組や、その取組と併せて行う業務効率化（生産性向上）の取組を</span></p><p><span style=\"color: rgb(0, 0, 0); font-size: 16px;\">支援するため、それに要する経費の一部を補助するものです。</span></p><p><br></p><p><br></p><p><strong style=\"font-size: 16px; color: rgb(0, 111, 173);\">■対象者</strong></p><p><span style=\"color: rgb(0, 0, 0); font-size: 16px;\">本補助金の補助対象者は、日本国内に所在する小規模事業者</span></p><p><span style=\"color: rgb(0, 0, 0); font-size: 16px;\">（日本国内に居住する個人、又は日本国内に本店を有する法人）等であることとします。</span></p><p><br></p><p><strong style=\"font-size: 16px; color: rgb(0, 111, 173);\">■支援カテゴリー</strong></p><p><span style=\"font-size: 16px; color: rgb(0, 0, 0); font-family: sans-serif;\">販路開拓</span></p><p><br></p><p><strong style=\"font-size: 16px; color: rgb(0, 111, 173);\">■補助金上限額</strong></p><p><span style=\"color: rgb(0, 0, 0); font-size: 16px;\">・補助上限： ２００万円</span></p><p><span style=\"color: rgb(0, 0, 0); font-size: 16px;\">　※インボイス特例対象事業者は、上記金額に 50 万円の上乗せ</span></p><p><span style=\"color: rgb(0, 0, 0); font-size: 16px;\"> （詳細は 公募要領 Ｐ.８をご参照ください）</span></p><p><br></p><p><strong style=\"font-size: 16px; color: rgb(0, 111, 173);\">■問合せ先</strong></p><p><span style=\"font-size: 16px; font-family: sans-serif; color: rgb(0, 0, 0);\">小規模事業者持続化補助金 事務局</span></p><p><span style=\"font-size: 16px; font-family: sans-serif; color: rgb(0, 0, 0);\">　電話番号　03-6739-3890</span></p><p><br></p><p><span style=\"font-size: 16px; font-family: sans-serif; color: rgb(0, 0, 0);\">Jグランツの操作に関する問い合わせ先</span></p><p><span style=\"font-size: 16px; font-family: sans-serif; color: rgb(0, 0, 0);\">　電話番号　03-6739-3890</span></p><p><br></p><p><span style=\"font-size: 16px; font-family: sans-serif; color: rgb(0, 0, 0);\">問い合わせの対応時間：9:00～12:00、13:00～17:00（土日祝日、年末年始除く）</span></p><p><br></p><p><strong style=\"font-size: 16px; color: rgb(0, 111, 173);\">■備考</strong></p><p><span style=\"font-size: 16px; color: rgb(0, 0, 0); font-family: sans-serif;\">公募要件等、申請様式等の詳細については公募要領、応募時提出資料・様式集、</span></p><p><span style=\"font-size: 16px; color: rgb(0, 0, 0); font-family: sans-serif;\">参考資料等を下記「参照URL」でご確認・ご利用ください。</span></p><p><br></p><p><strong style=\"color: rgb(0, 111, 173); font-size: 16px;\">■参照URL</strong><span style=\"color: rgb(255, 0, 0); font-size: 16px; font-family: sans-serif;\">（申請を行う前に必ず下記URLを参照・熟読してから申請してください。）</span></p><p><a href=\"https://r6.jizokukahojokin.info/sogyo/\" target=\"_blank\" style=\"color: rgb(0, 111, 173); font-size: 16px;\">小規模事業者持続化補助金トップ</a></p><p><a href=\"https://r6.jizokukahojokin.info/sogyo/doc/r6_koubover2_sogyo1.pdf\" target=\"_blank\" style=\"color: rgb(0, 111, 173); font-size: 16px;\">公募要領はこちらをクリック</a></p><p><a href=\"https://r6.jizokukahojokin.info/sogyo/doc/r6_youshiki_sogyo1.pdf\" target=\"_blank\" style=\"color: rgb(0, 111, 173); font-size: 16px;\">応募時提出資料・様式集はこちらをクリック</a></p><p><a href=\"https://r6.jizokukahojokin.info/sogyo/doc/r6_sankover1_sogyo1.pdf\" target=\"_blank\" style=\"color: rgb(0, 111, 173); font-size: 16px;\">参考資料はこちらをクリック</a></p><p><a href=\"https://r6.jizokukahojokin.info/sogyo/doc/r6_qa_sogyo1.pdf\" target=\"_blank\" style=\"color: rgb(0, 111, 173); font-size: 16px;\">よくあるご質問はこちらをクリック</a></p><p><a href=\"https://r6.jizokukahojokin.info/sogyo/doc/r6_kitei_250425_sogyo.pdf\" target=\"_blank\" style=\"color: rgb(0, 111, 173); font-size: 16px;\">交付規程はこちらをクリック</a></p><p><a href=\"https://r6.jizokukahojokin.info/sogyo/doc/r6_shinseimatome_sogyo1.zip\" target=\"_blank\" style=\"color: rgb(0, 111, 173); font-size: 16px;\">様式集ダウンロードはこちらをクリック</a></p><p><a href=\"https://r6.jizokukahojokin.info/sogyo/doc/r6_guidebook_sogyo1.pdf\" target=\"_blank\" style=\"color: rgb(0, 111, 173); font-size: 16px;\">ガイドブックはこちらをクリック</a></p>",
  "region": "prefecture",
  "prefectures": [
    "全国"
  ],
  "industries": [
    "漁業",
    "建設業",
    "製造業",
    "電気・ガス・熱供給・水道業",
    "情報通信業",
    "複合サービス事業",
    "サービス業（他に分類されないもの）",
    "農業",
    "林業",
    "鉱業",
    "採石業",
    "砂利採取業",
    "運輸業",
    "郵便業",
    "卸売業",
    "小売業",
    "金融業",
    "保険業",
    "不動産業",
    "物品賃貸業",
    "学術研究",
    "専門・技術サービス業",
    "宿泊業",
    "飲食サービス業",
    "生活関連サービス業",
    "娯楽業",
    "教育",
    "学習支援業",
    "医療",
    "福祉"
  ],
  "employeeMin": null,
  "employeeMax": 20,
  "purposes": [
    "人材育成",
    "販路拡大",
    "創業",
    "デジタル化"
  ],
  "status": "closed",
  "workflow": "小規模事業者持続化補助金＜創業型＞",
  "subsidizedRate": "２／３",
  "upperLimit": "2,000,000円",
  "lowerLimit": null,
  "startDate": "2025-05-01",
  "endDate": "2025-06-16",
  "source": "jgrants",
  "referenceUrl": "https://www.jgrants-portal.go.jp/subsidy/a0WJ200000CDN2pMAH",
  "updatedAt": "2026-04-19T18:29:25.073Z"
}