{
  "id": "a0WJ200000CDI22MAH",
  "slug": "a0wj200000cdi22mah",
  "title": "排出削減が困難な産業におけるエネルギー・製造プロセス転換支援事業",
  "overview": "",
  "detail": "<p><span style=\"font-size: 12px; color: rgb(51, 51, 51);\">経済産業省では、令和7年度「</span><span style=\"font-size: 11px;\">排出削減が困難な産業におけるエネルギー・製造プロセス転換支援事業</span><span style=\"font-size: 12px; color: rgb(51, 51, 51);\">」を実施する補助事業者を、以下の要領で広く募集します。</span></p><p><span style=\"font-size: 12px; color: rgb(51, 51, 51);\">なお、本公募は、令和7年度予算成立後、速やかに事業を開始できるようにするため、予算成立前に募集の手続を行うものです。補助事業者（執行団体）の決定や予算の執行は、令和7年度予算の成立が前提であり、今後、内容等が変更になることもありますのであらかじめ御了承ください。</span></p><p><br></p><p><strong style=\"color: rgb(0, 111, 173);\">■目的・概要</strong></p><p><span style=\"font-size: 11px;\">排出削減が困難な産業における排出量削減及び産業競争力強 化につなげるため、いち早い社会実装に繋がる下記に係る設備投資等を支援する。 </span></p><p><span style=\"font-size: 11px;\">（１）製造プロセス転換事業 </span></p><p><span style=\"font-size: 11px;\">多くのCO2排出を伴う従来の製造プロセスから、新たな低排出な 製造プロセスへ転換するため、下記に係る設備投資等を支援する。</span></p><p><span style=\"font-size: 11px;\"> ①鉄鋼 ・従来の高炉・転炉から大幅に排出を削減する革新的な電炉 への 転換、水素を活用した製鉄プロセスの導入</span></p><p><span style=\"font-size: 11px;\"> ②化学 ・廃プラスチック等を活用しナフサ原料の使用量を低減するケミ カルリサイクルへのプロセス転換 ・植物等から製造され、ライフサイクルを通じた排出量が低いバ イオ原料への原料転換</span></p><p><span style=\"font-size: 11px;\"> ③紙パルプ ・化石燃料由来製品等の代替素材となる可能性を有している 木質パルプを活用したバイオリファイナリー産業への転換 等 </span></p><p><span style=\"font-size: 11px;\">（２）自家発電設備等の燃料転換事業 石炭等を燃料とする自家発電設備</span></p><p><br></p><p><strong style=\"color: rgb(0, 111, 173);\">■問合せ先</strong></p><p>経済産業省　GXグループ</p><p>ＧＸ投資促進課</p><p>担　当：渡、金子、松下</p><p>メール：bzl-s-gx-investment@meti.go.jp</p><p>電　話：０３－３５０１－２０６７（直通）</p><p><br></p><p><strong style=\"color: rgb(0, 111, 173);\">■参照URL</strong></p><p><a href=\"https://www.meti.go.jp/main/yosan/yosan_fy2024/pr/pdf/pr_gx.pdf#page=7\" target=\"_blank\">https://www.meti.go.jp/main/yosan/yosan_fy2025/pr/pdf/pr_gx.pdf</a></p>",
  "region": "national",
  "prefectures": [],
  "industries": [
    "分類不能の産業"
  ],
  "employeeMin": null,
  "employeeMax": null,
  "purposes": [
    "設備投資",
    "省エネ"
  ],
  "status": "closed",
  "workflow": "排出削減が困難な産業におけるエネルギー・製造プロセス転換支援事業",
  "subsidizedRate": "定額",
  "upperLimit": "424,700,000,000円",
  "lowerLimit": null,
  "startDate": "2025-02-07",
  "endDate": "2025-02-28",
  "source": "jgrants",
  "referenceUrl": "https://www.jgrants-portal.go.jp/subsidy/a0WJ200000CDI22MAH",
  "updatedAt": "2026-04-19T18:29:24.148Z"
}